napari_cell_centroid_annotator/__init__.py
napari_cell_centroid_annotator/_reader.py
napari_cell_centroid_annotator/_version.py
napari_cell_centroid_annotator/_widget.py
napari_cell_centroid_annotator/napari.yaml
napari_cell_centroid_annotator/_tests/__init__.py
napari_cell_centroid_annotator/_tests/test_reader.py
napari_cell_centroid_annotator/_tests/test_widget.py
napari_cell_centroid_annotator-0.0.1.dist-info/LICENSE
napari_cell_centroid_annotator-0.0.1.dist-info/METADATA
napari_cell_centroid_annotator-0.0.1.dist-info/WHEEL
napari_cell_centroid_annotator-0.0.1.dist-info/entry_points.txt
napari_cell_centroid_annotator-0.0.1.dist-info/top_level.txt
napari_cell_centroid_annotator-0.0.1.dist-info/RECORD
