Metadata-Version: 2.1
Name: napari-cell-centroid-annotator
Version: 0.0.1
Summary: A simple plugin to annotate cell centroids in 3D images
Home-page: https://github.com/tim-vdl/napari-cell-centroid-annotator
Author: Tim Van De Looverbosch
Author-email: tim.vandelooverbosch@gmail.com
License: MIT
Project-URL: Bug Tracker, https://github.com/tim-vdl/napari-cell-centroid-annotator/issues
Project-URL: Documentation, https://github.com/tim-vdl/napari-cell-centroid-annotator#README.md
Project-URL: Source Code, https://github.com/tim-vdl/napari-cell-centroid-annotator
Project-URL: User Support, https://github.com/tim-vdl/napari-cell-centroid-annotator/issues
Classifier: Development Status :: 2 - Pre-Alpha
Classifier: Framework :: napari
Classifier: Intended Audience :: Developers
Classifier: License :: OSI Approved :: MIT License
Classifier: Operating System :: OS Independent
Classifier: Programming Language :: Python
Classifier: Programming Language :: Python :: 3
Classifier: Programming Language :: Python :: 3 :: Only
Classifier: Programming Language :: Python :: 3.8
Classifier: Programming Language :: Python :: 3.9
Classifier: Programming Language :: Python :: 3.10
Classifier: Topic :: Scientific/Engineering :: Image Processing
Requires-Python: >=3.8
License-File: LICENSE
Requires-Dist: numpy
Requires-Dist: pandas
Requires-Dist: tifffile
Requires-Dist: pathlib
Requires-Dist: napari
Requires-Dist: napari-plugin-engine
Requires-Dist: napari-layer-table
Requires-Dist: magicgui
Requires-Dist: qtpy
Provides-Extra: testing
Requires-Dist: tox ; extra == 'testing'
Requires-Dist: pytest ; extra == 'testing'
Requires-Dist: pytest-cov ; extra == 'testing'
Requires-Dist: pytest-qt ; extra == 'testing'
Requires-Dist: napari ; extra == 'testing'
Requires-Dist: pyqt5 ; extra == 'testing'
